nijas_keywords_extractor/__init__.py
nijas_keywords_extractor/main.py
nijas_keywords_extractor-1.dist-info/LICENSE
nijas_keywords_extractor-1.dist-info/METADATA
nijas_keywords_extractor-1.dist-info/WHEEL
nijas_keywords_extractor-1.dist-info/top_level.txt
nijas_keywords_extractor-1.dist-info/RECORD
