Metadata-Version: 2.1
Name: nijas-keywords-extractor
Version: 1
Summary: kinyarwanda keywords extractor
Author: Janvier Niyitegeka
Author-email: nijas2012@yahoo.com
Keywords: python,kinyarwanda,keywords
Classifier: Programming Language :: Python :: 3
Classifier: License :: OSI Approved :: MIT License
Classifier: Operating System :: OS Independent
License-File: LICENSE
Requires-Dist: pandas
Requires-Dist: numpy
Requires-Dist: yake
